full_adder.v
`timescale 1ps/100fs

module full_adder(
    input a,
    input b,
    input c_in ,
    output  sum,
    output  carry
  
);

assign #120  sum = a ^ b ^ c_in;
assign #80  carry = a & b & c_in;

endmodule // full_adder

full_adder_tb.v
`timescale 1ps/100fs
module full_adder_tb(); //testbench doesnt have any inputs or outputs
	reg a,b,c_in; 	//inputs are takens as reqisters ( they need to hold the value)
	wire sum,carry; //outputs are takens as wires in tb .
	full_adder dut(.*); //since all the inputs to the dut are the wires of same name
	initial begin
		$dumpfile("full_adder_tb.vcd"); 	
		$dumpvars(0,full_adder_tb);			//first argument is the level of debugging
								//level 0 will log all the variable even in 
		//sub modules 
		//whereas level 1 will log only the ones in the top module 
		a = 0;
		b = 0; c_in = 0;
		#200;
		a = 0;
		b = 1; c_in = 1;
		#200;
		a = 1;
		b = 0; c_in = 0;
		#200;
		a = 1;
		b = 1; c_in = 1;
		#200;  //assign reister values and wait for 100 ps 
	end
endmodule

full_adder_tb.vcd
$date
	Fri Nov  9 16:41:29 2018
$end
$version
	Icarus Verilog
$end
$timescale
	100fs
$end
$scope module full_adder_tb $end
$var wire 1 ! sum $end
$var wire 1 " carry $end
$var reg 1 # a $end
$var reg 1 $ b $end
$var reg 1 % c_in $end
$scope module dut $end
$var wire 1 # a $end
$var wire 1 $ b $end
$var wire 1 % c_in $end
$var wire 1 " carry $end
$var wire 1 ! sum $end
$upscope $end
$upscope $end
$enddefinitions $end
#0
$dumpvars
0%
0$
0#
x"
x!
$end
#800
0"
#1200
0!
#2000
1%
1$
#4000
0%
0$
1#
#5200
1!
#6000
1%
1$
#6800
1"
